autofj/__init__.py
autofj/autofj.py
autofj/datasets.py
autofj/negative_rule.py
autofj/utils.py
autofj/benchmark/.DS_Store
autofj/benchmark/Amphibian/gt.csv
autofj/benchmark/Amphibian/left.csv
autofj/benchmark/Amphibian/right.csv
autofj/benchmark/ArtificialSatellite/gt.csv
autofj/benchmark/ArtificialSatellite/left.csv
autofj/benchmark/ArtificialSatellite/right.csv
autofj/benchmark/Artwork/gt.csv
autofj/benchmark/Artwork/left.csv
autofj/benchmark/Artwork/right.csv
autofj/benchmark/Award/gt.csv
autofj/benchmark/Award/left.csv
autofj/benchmark/Award/right.csv
autofj/benchmark/BasketballTeam/gt.csv
autofj/benchmark/BasketballTeam/left.csv
autofj/benchmark/BasketballTeam/right.csv
autofj/benchmark/Case/gt.csv
autofj/benchmark/Case/left.csv
autofj/benchmark/Case/right.csv
autofj/benchmark/ChristianBishop/gt.csv
autofj/benchmark/ChristianBishop/left.csv
autofj/benchmark/ChristianBishop/right.csv
autofj/benchmark/ClericalAdministrativeRegion/gt.csv
autofj/benchmark/ClericalAdministrativeRegion/left.csv
autofj/benchmark/ClericalAdministrativeRegion/right.csv
autofj/benchmark/Country/gt.csv
autofj/benchmark/Country/left.csv
autofj/benchmark/Country/right.csv
autofj/benchmark/Device/gt.csv
autofj/benchmark/Device/left.csv
autofj/benchmark/Device/right.csv
autofj/benchmark/Drug/gt.csv
autofj/benchmark/Drug/left.csv
autofj/benchmark/Drug/right.csv
autofj/benchmark/Election/gt.csv
autofj/benchmark/Election/left.csv
autofj/benchmark/Election/right.csv
autofj/benchmark/Enzyme/gt.csv
autofj/benchmark/Enzyme/left.csv
autofj/benchmark/Enzyme/right.csv
autofj/benchmark/EthnicGroup/gt.csv
autofj/benchmark/EthnicGroup/left.csv
autofj/benchmark/EthnicGroup/right.csv
autofj/benchmark/FootballLeagueSeason/gt.csv
autofj/benchmark/FootballLeagueSeason/left.csv
autofj/benchmark/FootballLeagueSeason/right.csv
autofj/benchmark/FootballMatch/gt.csv
autofj/benchmark/FootballMatch/left.csv
autofj/benchmark/FootballMatch/right.csv
autofj/benchmark/Galaxy/gt.csv
autofj/benchmark/Galaxy/left.csv
autofj-0.0.6.dist-info/METADATA
autofj-0.0.6.dist-info/WHEEL
autofj-0.0.6.dist-info/top_level.txt
autofj-0.0.6.dist-info/RECORD
