Metadata-Version: 2.1
Name: autofj
Version: 0.0.6
Summary: Auto-Program Fuzzy Similarity Joins Without Labeled Examples
Home-page: https://github.com/chu-data-lab/AutomaticFuzzyJoin
Author: Peng Li
Author-email: lipengpublic@gmail.com
License: UNKNOWN
Platform: UNKNOWN
Classifier: Programming Language :: Python :: 3
Classifier: License :: OSI Approved :: MIT License
Classifier: Operating System :: OS Independent
Requires-Python: >=3.7
Requires-Dist: numpy
Requires-Dist: pandas
Requires-Dist: nltk
Requires-Dist: ngram
Requires-Dist: editdistance
Requires-Dist: jellyfish
Requires-Dist: spacy
